d3LineGraphSrc/__init__.py
d3LineGraphSrc/frontend/build/asset-manifest.json
d3LineGraphSrc/frontend/build/bootstrap.min.css
d3LineGraphSrc/frontend/build/index.html
d3LineGraphSrc/frontend/build/static/js/main.a5e71909.js
d3LineGraphSrc/frontend/build/static/js/main.a5e71909.js.LICENSE.txt
d3LineGraphSrc/frontend/build/static/js/main.a5e71909.js.map
st_d3_Line_Graph_Comparison-0.2.6.dist-info/METADATA
st_d3_Line_Graph_Comparison-0.2.6.dist-info/WHEEL
st_d3_Line_Graph_Comparison-0.2.6.dist-info/top_level.txt
st_d3_Line_Graph_Comparison-0.2.6.dist-info/RECORD
