Metadata-Version: 2.1
Name: st-d3-Line-Graph-Comparison
Version: 0.2.6
Home-page: 
Author: 
Author-email: 
Requires-Python: >=3.6
Requires-Dist: streamlit (>=0.63)
